scrapeless/__init__.py
scrapeless/client.py
scrapeless/env.py
scrapeless/error.py
scrapeless/actor/__init__.py
scrapeless/actor/index.py
scrapeless/scraping_browser/__init__.py
scrapeless/scraping_browser/base.py
scrapeless/scraping_browser/playwright.py
scrapeless/scraping_browser/pyppeteer.py
scrapeless/scraping_crawl/__init__.py
scrapeless/scraping_crawl/index.py
scrapeless/services/__init__.py
scrapeless/services/actor.py
scrapeless/services/base.py
scrapeless/services/browser.py
scrapeless/services/captcha.py
scrapeless/services/deepserp.py
scrapeless/services/extension.py
scrapeless/services/profiles.py
scrapeless/services/proxies.py
scrapeless/services/scraping.py
scrapeless/services/universal.py
scrapeless/services/crawl/__init__.py
scrapeless/services/crawl/base.py
scrapeless/services/crawl/crawl.py
scrapeless/services/crawl/index.py
scrapeless/services/crawl/scrape.py
scrapeless/services/storage/__init__.py
scrapeless/services/storage/dataset.py
scrapeless/services/storage/index.py
scrapeless/services/storage/kv.py
scrapeless/services/storage/object.py
scrapeless/services/storage/queue.py
scrapeless/types/__init__.py
scrapeless/types/actor.py
scrapeless/types/base.py
scrapeless/types/browser.py
scrapeless/types/captcha.py
scrapeless/types/config.py
scrapeless/types/deepserp.py
scrapeless/types/extension.py
scrapeless/types/profile.py
scrapeless/types/proxies.py
scrapeless/types/runner.py
scrapeless/types/scraping.py
scrapeless/types/scraping_crawl.py
scrapeless/types/storage.py
scrapeless/types/universal.py
scrapeless/universal/__init__.py
scrapeless/universal/index.py
scrapeless/utils/__init__.py
scrapeless/utils/logger.py
scrapeless/utils/utils.py
scrapeless-1.2.1.dist-info/licenses/LICENSE
scrapeless-1.2.1.dist-info/METADATA
scrapeless-1.2.1.dist-info/WHEEL
scrapeless-1.2.1.dist-info/top_level.txt
scrapeless-1.2.1.dist-info/RECORD
