Metadata-Version: 2.4
Name: scrapeless
Version: 1.2.1
Summary: scrapeless python sdk
Home-page: https://github.com/scrapeless-ai/sdk-python
Author: scrapelessteam
Author-email: scrapelessteam@gmail.com
License: MIT
Project-URL: Documentation, https://github.com/scrapeless-ai/sdk-python#readme
Project-URL: Source, https://github.com/scrapeless-ai/sdk-python
Keywords: scrapeless,browserless,scraping browser,scraping,web unlocker,captcha solver,rotate proxy
Requires-Python: >=3.8
License-File: LICENSE
Requires-Dist: requests>=2.25.0
Dynamic: author
Dynamic: author-email
Dynamic: description
Dynamic: description-content-type
Dynamic: home-page
Dynamic: keywords
Dynamic: license
Dynamic: license-file
Dynamic: project-url
Dynamic: requires-dist
Dynamic: requires-python
Dynamic: summary
